{
  "press": [
    {
      "image": "./src/assets/face.png",
      "date": "06.10.2021",
      "link": "DELFI",
      "text": "Андриан Фадеев: «Не люблю артистов, у которых в глазах только доллары»"
    },
    {
      "image": "./src/assets/donKihot.png",
      "date": "27.09.2021",
      "link": "DELFI / SHOW TIME",
      "text": "Испанский огонь и питерская прописка: «Дон Кихот» на «Золотой маске в Латвии»"
    },
    {
      "image": "./src/assets/piterDonKihot.png",
      "date": "18.10.2021",
      "link": "RUS.LSM.lv",
      "text": "Петербургский «Дон Кихот» без глянца, на радость народу — роскошно!"
    },
    {
      "image": "./src/assets/jackobson.png",
      "date": "30.09.2021",
      "link": "ИА ИНТЕРФАКС",
      "text": "Петербургский Театр балета Якобсона впервые выступит в Бахрейне"
    },
    {
      "image": "./src/assets/mariinka.png",
      "date": "24.09.2021",
      "link": "САНКТ-ПЕТЕРБУРГ, НОВОСТИ",
      "text": "Театр балета имени Л. Якобсона откроет 53-й сезон спектаклями на сцене Мариинки"
    },
    {
      "image": "./src/assets/karelia.png",
      "date": "05.10.2021",
      "link": "ПЕТРОЗАВОДСК ГОВОРИТ",
      "text": "Уникальный театр балета покажет необычную программу в Карелии"
    },
    {
      "image": "./src/assets/jisel.png",
      "date": "11.06.2021",
      "link": "РОССИЙСКАЯ ГАЗЕТА",
      "text": "Экзамен для Жизели"
    }
  ]
}